EXPLDA/__init__.py
EXPLDA-0.4.dist-info/LICENSE.txt
EXPLDA-0.4.dist-info/METADATA
EXPLDA-0.4.dist-info/WHEEL
EXPLDA-0.4.dist-info/top_level.txt
EXPLDA-0.4.dist-info/RECORD
