Metadata-Version: 2.1
Name: EXPLDA
Version: 0.4
Summary: This package is used to replace the missing values in the dataframe with mean or median or mode along with normalizing the data using standard scaler technique
Home-page: UNKNOWN
Author: Ankit Marwaha
Author-email: ankitmarwaha7@gmail.com
License: UNKNOWN
Platform: UNKNOWN
Classifier: Programming Language :: Python :: 3.6
Classifier: Programming Language :: Python :: 3.7
Classifier: Programming Language :: Python :: 3.8
Classifier: License :: OSI Approved :: MIT License
Classifier: Operating System :: OS Independent
Requires-Dist: pandas
Requires-Dist: sklearn
